claudecut/__init__.py
claudecut/agent.py
claudecut/agent_tools.py
claudecut/caption_renderer.py
claudecut/video_editor.py
claudecut-0.1.4.dist-info/METADATA
claudecut-0.1.4.dist-info/WHEEL
claudecut-0.1.4.dist-info/entry_points.txt
claudecut-0.1.4.dist-info/licenses/LICENSE
claudecut-0.1.4.dist-info/RECORD
